{
    "records": {
        "r1": {
            "version": "1.1",
            "repeat": {
                "count": "1",
                "duration": "0",
                "sel": "count"
            },
            "timestamp": "1745971281875",
            "interval": "0",
            "speed": "1",
            "title": "퀘완료",
            "events": [
                {
                    "position": {
                        "x": "0.899325073",
                        "y": "0.0529999994"
                    },
                    "ms": "1500",
                    "type": "513",
                    "detail": "1374208",
                    "data": "0"
                },
                {
                    "position": {
                        "x": "0.899325073",
                        "y": "0.0529999994"
                    },
                    "ms": "1580",
                    "type": "514",
                    "detail": "1374208",
                    "data": "0"
                },
                {
                    "position": {
                        "x": "0.112485938",
                        "y": "0.148000002"
                    },
                    "ms": "2502",
                    "type": "513",
                    "detail": "1374208",
                    "data": "0"
                },
                {
                    "position": {
                        "x": "0.112485938",
                        "y": "0.148000002"
                    },
                    "ms": "2586",
                    "type": "514",
                    "detail": "1374208",
                    "data": "0"
                },
                {
                    "position": {
                        "x": "0.112485938",
                        "y": "0.148000002"
                    },
                    "ms": "2654",
                    "type": "513",
                    "detail": "1374208",
                    "data": "0"
                },
                {
                    "position": {
                        "x": "0.112485938",
                        "y": "0.148000002"
                    },
                    "ms": "2737",
                    "type": "514",
                    "detail": "1374208",
                    "data": "0"
                },
                {
                    "position": {
                        "x": "0.538245201",
                        "y": "0.256000012"
                    },
                    "ms": "3680",
                    "type": "513",
                    "detail": "1374208",
                    "data": "0"
                },
                {
                    "position": {
                        "x": "0.538245201",
                        "y": "0.256000012"
                    },
                    "ms": "3763",
                    "type": "514",
                    "detail": "1374208",
                    "data": "0"
                },
                {
                    "position": {
                        "x": "0.538245201",
                        "y": "0.256000012"
                    },
                    "ms": "3813",
                    "type": "513",
                    "detail": "1374208",
                    "data": "0"
                },
                {
                    "position": {
                        "x": "0.538245201",
                        "y": "0.256000012"
                    },
                    "ms": "3913",
                    "type": "514",
                    "detail": "1374208",
                    "data": "0"
                },
                {
                    "position": {
                        "x": "0.538245201",
                        "y": "0.256000012"
                    },
                    "ms": "3968",
                    "type": "513",
                    "detail": "1374208",
                    "data": "0"
                },
                {
                    "position": {
                        "x": "0.538245201",
                        "y": "0.256000012"
                    },
                    "ms": "4067",
                    "type": "514",
                    "detail": "1374208",
                    "data": "0"
                },
                {
                    "position": {
                        "x": "0.538245201",
                        "y": "0.256000012"
                    },
                    "ms": "4134",
                    "type": "513",
                    "detail": "1374208",
                    "data": "0"
                },
                {
                    "position": {
                        "x": "0.538245201",
                        "y": "0.256000012"
                    },
                    "ms": "4222",
                    "type": "514",
                    "detail": "1374208",
                    "data": "0"
                },
                {
                    "position": {
                        "x": "0.538245201",
                        "y": "0.256000012"
                    },
                    "ms": "4291",
                    "type": "513",
                    "detail": "1374208",
                    "data": "0"
                },
                {
                    "position": {
                        "x": "0.538245201",
                        "y": "0.256000012"
                    },
                    "ms": "4383",
                    "type": "514",
                    "detail": "1374208",
                    "data": "0"
                },
                {
                    "position": {
                        "x": "0.538245201",
                        "y": "0.256000012"
                    },
                    "ms": "4437",
                    "type": "513",
                    "detail": "1374208",
                    "data": "0"
                },
                {
                    "position": {
                        "x": "0.538245201",
                        "y": "0.256000012"
                    },
                    "ms": "4530",
                    "type": "514",
                    "detail": "1374208",
                    "data": "0"
                },
                {
                    "position": {
                        "x": "0.538245201",
                        "y": "0.256000012"
                    },
                    "ms": "4597",
                    "type": "513",
                    "detail": "1374208",
                    "data": "0"
                },
                {
                    "position": {
                        "x": "0.538245201",
                        "y": "0.256000012"
                    },
                    "ms": "4700",
                    "type": "514",
                    "detail": "1374208",
                    "data": "0"
                },
                {
                    "position": {
                        "x": "0.538245201",
                        "y": "0.256000012"
                    },
                    "ms": "4751",
                    "type": "513",
                    "detail": "1374208",
                    "data": "0"
                },
                {
                    "position": {
                        "x": "0.538245201",
                        "y": "0.256000012"
                    },
                    "ms": "4851",
                    "type": "514",
                    "detail": "1374208",
                    "data": "0"
                },
                {
                    "position": {
                        "x": "0.538245201",
                        "y": "0.256000012"
                    },
                    "ms": "4916",
                    "type": "513",
                    "detail": "1374208",
                    "data": "0"
                },
                {
                    "position": {
                        "x": "0.538245201",
                        "y": "0.256000012"
                    },
                    "ms": "5017",
                    "type": "514",
                    "detail": "1374208",
                    "data": "0"
                },
                {
                    "position": {
                        "x": "0.538245201",
                        "y": "0.256000012"
                    },
                    "ms": "5085",
                    "type": "513",
                    "detail": "1374208",
                    "data": "0"
                },
                {
                    "position": {
                        "x": "0.538245201",
                        "y": "0.256000012"
                    },
                    "ms": "5185",
                    "type": "514",
                    "detail": "1374208",
                    "data": "0"
                },
                {
                    "position": {
                        "x": "0.538245201",
                        "y": "0.256000012"
                    },
                    "ms": "5236",
                    "type": "513",
                    "detail": "1374208",
                    "data": "0"
                },
                {
                    "position": {
                        "x": "0.538245201",
                        "y": "0.256000012"
                    },
                    "ms": "5336",
                    "type": "514",
                    "detail": "1374208",
                    "data": "0"
                },
                {
                    "position": {
                        "x": "0.538245201",
                        "y": "0.256000012"
                    },
                    "ms": "5387",
                    "type": "513",
                    "detail": "1374208",
                    "data": "0"
                },
                {
                    "position": {
                        "x": "0.538245201",
                        "y": "0.256000012"
                    },
                    "ms": "5488",
                    "type": "514",
                    "detail": "1374208",
                    "data": "0"
                },
                {
                    "position": {
                        "x": "0.538245201",
                        "y": "0.256000012"
                    },
                    "ms": "5554",
                    "type": "513",
                    "detail": "1374208",
                    "data": "0"
                },
                {
                    "position": {
                        "x": "0.538245201",
                        "y": "0.256000012"
                    },
                    "ms": "5653",
                    "type": "514",
                    "detail": "1374208",
                    "data": "0"
                },
                {
                    "position": {
                        "x": "0.538245201",
                        "y": "0.256000012"
                    },
                    "ms": "5719",
                    "type": "513",
                    "detail": "1374208",
                    "data": "0"
                },
                {
                    "position": {
                        "x": "0.538245201",
                        "y": "0.256000012"
                    },
                    "ms": "5818",
                    "type": "514",
                    "detail": "1374208",
                    "data": "0"
                },
                {
                    "position": {
                        "x": "0.538245201",
                        "y": "0.256000012"
                    },
                    "ms": "5885",
                    "type": "513",
                    "detail": "1374208",
                    "data": "0"
                },
                {
                    "position": {
                        "x": "0.538245201",
                        "y": "0.256000012"
                    },
                    "ms": "5969",
                    "type": "514",
                    "detail": "1374208",
                    "data": "0"
                },
                {
                    "position": {
                        "x": "0.538245201",
                        "y": "0.256000012"
                    },
                    "ms": "6055",
                    "type": "513",
                    "detail": "1374208",
                    "data": "0"
                },
                {
                    "position": {
                        "x": "0.538245201",
                        "y": "0.256000012"
                    },
                    "ms": "6121",
                    "type": "514",
                    "detail": "1374208",
                    "data": "0"
                },
                {
                    "position": {
                        "x": "0.538245201",
                        "y": "0.256000012"
                    },
                    "ms": "6203",
                    "type": "513",
                    "detail": "1374208",
                    "data": "0"
                },
                {
                    "position": {
                        "x": "0.538245201",
                        "y": "0.256000012"
                    },
                    "ms": "6285",
                    "type": "514",
                    "detail": "1374208",
                    "data": "0"
                },
                {
                    "position": {
                        "x": "0.538245201",
                        "y": "0.256000012"
                    },
                    "ms": "6357",
                    "type": "513",
                    "detail": "1374208",
                    "data": "0"
                },
                {
                    "position": {
                        "x": "0.538245201",
                        "y": "0.256000012"
                    },
                    "ms": "6453",
                    "type": "514",
                    "detail": "1374208",
                    "data": "0"
                },
                {
                    "position": {
                        "x": "0.538245201",
                        "y": "0.256000012"
                    },
                    "ms": "6521",
                    "type": "513",
                    "detail": "1374208",
                    "data": "0"
                },
                {
                    "position": {
                        "x": "0.538245201",
                        "y": "0.256000012"
                    },
                    "ms": "6604",
                    "type": "514",
                    "detail": "1374208",
                    "data": "0"
                },
                {
                    "position": {
                        "x": "0.538245201",
                        "y": "0.256000012"
                    },
                    "ms": "6689",
                    "type": "513",
                    "detail": "1374208",
                    "data": "0"
                },
                {
                    "position": {
                        "x": "0.538245201",
                        "y": "0.256000012"
                    },
                    "ms": "6771",
                    "type": "514",
                    "detail": "1374208",
                    "data": "0"
                },
                {
                    "position": {
                        "x": "0.538245201",
                        "y": "0.256000012"
                    },
                    "ms": "6838",
                    "type": "513",
                    "detail": "1374208",
                    "data": "0"
                },
                {
                    "position": {
                        "x": "0.538245201",
                        "y": "0.256000012"
                    },
                    "ms": "6937",
                    "type": "514",
                    "detail": "1374208",
                    "data": "0"
                },
                {
                    "position": {
                        "x": "0.538245201",
                        "y": "0.256000012"
                    },
                    "ms": "7008",
                    "type": "513",
                    "detail": "1374208",
                    "data": "0"
                },
                {
                    "position": {
                        "x": "0.538245201",
                        "y": "0.256000012"
                    },
                    "ms": "7090",
                    "type": "514",
                    "detail": "1374208",
                    "data": "0"
                },
                {
                    "position": {
                        "x": "0.538245201",
                        "y": "0.256000012"
                    },
                    "ms": "7157",
                    "type": "513",
                    "detail": "1374208",
                    "data": "0"
                },
                {
                    "position": {
                        "x": "0.538245201",
                        "y": "0.256000012"
                    },
                    "ms": "7257",
                    "type": "514",
                    "detail": "1374208",
                    "data": "0"
                },
                {
                    "position": {
                        "x": "0.538245201",
                        "y": "0.256000012"
                    },
                    "ms": "7323",
                    "type": "513",
                    "detail": "1374208",
                    "data": "0"
                },
                {
                    "position": {
                        "x": "0.538245201",
                        "y": "0.256000012"
                    },
                    "ms": "7407",
                    "type": "514",
                    "detail": "1374208",
                    "data": "0"
                },
                {
                    "position": {
                        "x": "0.538245201",
                        "y": "0.256000012"
                    },
                    "ms": "7475",
                    "type": "513",
                    "detail": "1374208",
                    "data": "0"
                },
                {
                    "position": {
                        "x": "0.538245201",
                        "y": "0.256000012"
                    },
                    "ms": "7560",
                    "type": "514",
                    "detail": "1374208",
                    "data": "0"
                },
                {
                    "position": {
                        "x": "0.23565805",
                        "y": "0.140000001"
                    },
                    "ms": "7908",
                    "type": "513",
                    "detail": "1374208",
                    "data": "0"
                },
                {
                    "position": {
                        "x": "0.23565805",
                        "y": "0.140000001"
                    },
                    "ms": "7975",
                    "type": "514",
                    "detail": "1374208",
                    "data": "0"
                },
                {
                    "position": {
                        "x": "0.23565805",
                        "y": "0.140000001"
                    },
                    "ms": "8044",
                    "type": "513",
                    "detail": "1374208",
                    "data": "0"
                },
                {
                    "position": {
                        "x": "0.23565805",
                        "y": "0.140000001"
                    },
                    "ms": "8144",
                    "type": "514",
                    "detail": "1374208",
                    "data": "0"
                },
                {
                    "position": {
                        "x": "0.23565805",
                        "y": "0.140000001"
                    },
                    "ms": "8212",
                    "type": "513",
                    "detail": "1374208",
                    "data": "0"
                },
                {
                    "position": {
                        "x": "0.23565805",
                        "y": "0.140000001"
                    },
                    "ms": "8318",
                    "type": "514",
                    "detail": "1374208",
                    "data": "0"
                },
                {
                    "position": {
                        "x": "0.23565805",
                        "y": "0.140000001"
                    },
                    "ms": "8368",
                    "type": "513",
                    "detail": "1374208",
                    "data": "0"
                },
                {
                    "position": {
                        "x": "0.236782908",
                        "y": "0.140000001"
                    },
                    "ms": "8451",
                    "type": "512",
                    "detail": "1374208",
                    "data": "0"
                },
                {
                    "position": {
                        "x": "0.238470197",
                        "y": "0.140000001"
                    },
                    "ms": "8457",
                    "type": "512",
                    "detail": "1374208",
                    "data": "0"
                },
                {
                    "position": {
                        "x": "0.239595056",
                        "y": "0.140000001"
                    },
                    "ms": "8462",
                    "type": "512",
                    "detail": "1374208",
                    "data": "0"
                },
                {
                    "position": {
                        "x": "0.239595056",
                        "y": "0.140000001"
                    },
                    "ms": "8462",
                    "type": "514",
                    "detail": "1374208",
                    "data": "0"
                },
                {
                    "position": {
                        "x": "0.525871754",
                        "y": "0.256000012"
                    },
                    "ms": "8863",
                    "type": "513",
                    "detail": "1374208",
                    "data": "0"
                },
                {
                    "position": {
                        "x": "0.525871754",
                        "y": "0.256000012"
                    },
                    "ms": "8947",
                    "type": "514",
                    "detail": "1374208",
                    "data": "0"
                },
                {
                    "position": {
                        "x": "0.525871754",
                        "y": "0.256000012"
                    },
                    "ms": "9013",
                    "type": "513",
                    "detail": "1374208",
                    "data": "0"
                },
                {
                    "position": {
                        "x": "0.525871754",
                        "y": "0.256000012"
                    },
                    "ms": "9113",
                    "type": "514",
                    "detail": "1374208",
                    "data": "0"
                },
                {
                    "position": {
                        "x": "0.525871754",
                        "y": "0.256000012"
                    },
                    "ms": "9176",
                    "type": "513",
                    "detail": "1374208",
                    "data": "0"
                },
                {
                    "position": {
                        "x": "0.525871754",
                        "y": "0.256000012"
                    },
                    "ms": "9278",
                    "type": "514",
                    "detail": "1374208",
                    "data": "0"
                },
                {
                    "position": {
                        "x": "0.523622036",
                        "y": "0.256999999"
                    },
                    "ms": "9346",
                    "type": "513",
                    "detail": "1374208",
                    "data": "0"
                },
                {
                    "position": {
                        "x": "0.523622036",
                        "y": "0.256999999"
                    },
                    "ms": "9447",
                    "type": "514",
                    "detail": "1374208",
                    "data": "0"
                },
                {
                    "position": {
                        "x": "0.523622036",
                        "y": "0.256999999"
                    },
                    "ms": "9513",
                    "type": "513",
                    "detail": "1374208",
                    "data": "0"
                },
                {
                    "position": {
                        "x": "0.523622036",
                        "y": "0.257999986"
                    },
                    "ms": "9597",
                    "type": "512",
                    "detail": "1374208",
                    "data": "0"
                },
                {
                    "position": {
                        "x": "0.523059607",
                        "y": "0.257999986"
                    },
                    "ms": "9603",
                    "type": "512",
                    "detail": "1374208",
                    "data": "0"
                },
                {
                    "position": {
                        "x": "0.523059607",
                        "y": "0.257999986"
                    },
                    "ms": "9608",
                    "type": "514",
                    "detail": "1374208",
                    "data": "0"
                },
                {
                    "position": {
                        "x": "0.51968503",
                        "y": "0.263999999"
                    },
                    "ms": "9669",
                    "type": "513",
                    "detail": "1374208",
                    "data": "0"
                },
                {
                    "position": {
                        "x": "0.51968503",
                        "y": "0.263999999"
                    },
                    "ms": "9771",
                    "type": "514",
                    "detail": "1374208",
                    "data": "0"
                },
                {
                    "position": {
                        "x": "0.51968503",
                        "y": "0.263999999"
                    },
                    "ms": "9837",
                    "type": "513",
                    "detail": "1374208",
                    "data": "0"
                },
                {
                    "position": {
                        "x": "0.51968503",
                        "y": "0.263999999"
                    },
                    "ms": "9937",
                    "type": "514",
                    "detail": "1374208",
                    "data": "0"
                },
                {
                    "position": {
                        "x": "0.51968503",
                        "y": "0.263999999"
                    },
                    "ms": "10005",
                    "type": "513",
                    "detail": "1374208",
                    "data": "0"
                },
                {
                    "position": {
                        "x": "0.51968503",
                        "y": "0.263999999"
                    },
                    "ms": "10105",
                    "type": "514",
                    "detail": "1374208",
                    "data": "0"
                },
                {
                    "position": {
                        "x": "0.516872883",
                        "y": "0.266000003"
                    },
                    "ms": "10173",
                    "type": "513",
                    "detail": "1374208",
                    "data": "0"
                },
                {
                    "position": {
                        "x": "0.516872883",
                        "y": "0.266000003"
                    },
                    "ms": "10255",
                    "type": "514",
                    "detail": "1374208",
                    "data": "0"
                },
                {
                    "position": {
                        "x": "0.514623165",
                        "y": "0.26699999"
                    },
                    "ms": "10322",
                    "type": "513",
                    "detail": "1374208",
                    "data": "0"
                },
                {
                    "position": {
                        "x": "0.514623165",
                        "y": "0.26699999"
                    },
                    "ms": "10422",
                    "type": "514",
                    "detail": "1374208",
                    "data": "0"
                },
                {
                    "position": {
                        "x": "0.514623165",
                        "y": "0.26699999"
                    },
                    "ms": "10488",
                    "type": "513",
                    "detail": "1374208",
                    "data": "0"
                },
                {
                    "position": {
                        "x": "0.514623165",
                        "y": "0.26699999"
                    },
                    "ms": "10592",
                    "type": "514",
                    "detail": "1374208",
                    "data": "0"
                },
                {
                    "position": {
                        "x": "0.514623165",
                        "y": "0.26699999"
                    },
                    "ms": "10663",
                    "type": "513",
                    "detail": "1374208",
                    "data": "0"
                },
                {
                    "position": {
                        "x": "0.514623165",
                        "y": "0.26699999"
                    },
                    "ms": "10746",
                    "type": "514",
                    "detail": "1374208",
                    "data": "0"
                },
                {
                    "position": {
                        "x": "0.514623165",
                        "y": "0.26699999"
                    },
                    "ms": "10830",
                    "type": "513",
                    "detail": "1374208",
                    "data": "0"
                },
                {
                    "position": {
                        "x": "0.514623165",
                        "y": "0.26699999"
                    },
                    "ms": "10930",
                    "type": "514",
                    "detail": "1374208",
                    "data": "0"
                },
                {
                    "position": {
                        "x": "0.514623165",
                        "y": "0.26699999"
                    },
                    "ms": "10997",
                    "type": "513",
                    "detail": "1374208",
                    "data": "0"
                },
                {
                    "position": {
                        "x": "0.514623165",
                        "y": "0.26699999"
                    },
                    "ms": "11080",
                    "type": "514",
                    "detail": "1374208",
                    "data": "0"
                },
                {
                    "position": {
                        "x": "0.514623165",
                        "y": "0.26699999"
                    },
                    "ms": "11164",
                    "type": "513",
                    "detail": "1374208",
                    "data": "0"
                },
                {
                    "position": {
                        "x": "0.514623165",
                        "y": "0.266000003"
                    },
                    "ms": "11169",
                    "type": "512",
                    "detail": "1374208",
                    "data": "0"
                },
                {
                    "position": {
                        "x": "0.514623165",
                        "y": "0.266000003"
                    },
                    "ms": "11249",
                    "type": "514",
                    "detail": "1374208",
                    "data": "0"
                },
                {
                    "position": {
                        "x": "0.514060736",
                        "y": "0.266000003"
                    },
                    "ms": "11316",
                    "type": "513",
                    "detail": "1374208",
                    "data": "0"
                },
                {
                    "position": {
                        "x": "0.514060736",
                        "y": "0.264999986"
                    },
                    "ms": "11333",
                    "type": "512",
                    "detail": "1374208",
                    "data": "0"
                },
                {
                    "position": {
                        "x": "0.514060736",
                        "y": "0.264999986"
                    },
                    "ms": "11400",
                    "type": "514",
                    "detail": "1374208",
                    "data": "0"
                },
                {
                    "position": {
                        "x": "0.514060736",
                        "y": "0.264999986"
                    },
                    "ms": "11477",
                    "type": "513",
                    "detail": "1374208",
                    "data": "0"
                },
                {
                    "position": {
                        "x": "0.513498306",
                        "y": "0.264999986"
                    },
                    "ms": "11568",
                    "type": "512",
                    "detail": "1374208",
                    "data": "0"
                },
                {
                    "position": {
                        "x": "0.513498306",
                        "y": "0.264999986"
                    },
                    "ms": "11574",
                    "type": "514",
                    "detail": "1374208",
                    "data": "0"
                },
                {
                    "position": {
                        "x": "0.360517442",
                        "y": "0.147"
                    },
                    "ms": "11930",
                    "type": "513",
                    "detail": "1374208",
                    "data": "0"
                },
                {
                    "position": {
                        "x": "0.360517442",
                        "y": "0.147"
                    },
                    "ms": "12013",
                    "type": "514",
                    "detail": "1374208",
                    "data": "0"
                },
                {
                    "position": {
                        "x": "0.360517442",
                        "y": "0.147"
                    },
                    "ms": "12091",
                    "type": "513",
                    "detail": "1374208",
                    "data": "0"
                },
                {
                    "position": {
                        "x": "0.360517442",
                        "y": "0.147"
                    },
                    "ms": "12164",
                    "type": "514",
                    "detail": "1374208",
                    "data": "0"
                },
                {
                    "position": {
                        "x": "0.360517442",
                        "y": "0.147"
                    },
                    "ms": "12251",
                    "type": "513",
                    "detail": "1374208",
                    "data": "0"
                },
                {
                    "position": {
                        "x": "0.360517442",
                        "y": "0.147"
                    },
                    "ms": "12334",
                    "type": "514",
                    "detail": "1374208",
                    "data": "0"
                },
                {
                    "position": {
                        "x": "0.89257592",
                        "y": "0.947000027"
                    },
                    "ms": "12885",
                    "type": "513",
                    "detail": "1374208",
                    "data": "0"
                },
                {
                    "position": {
                        "x": "0.89257592",
                        "y": "0.947000027"
                    },
                    "ms": "12973",
                    "type": "514",
                    "detail": "1374208",
                    "data": "0"
                },
                {
                    "position": {
                        "x": "0.886389196",
                        "y": "0.944999993"
                    },
                    "ms": "13047",
                    "type": "513",
                    "detail": "1374208",
                    "data": "0"
                },
                {
                    "position": {
                        "x": "0.886389196",
                        "y": "0.944999993"
                    },
                    "ms": "13134",
                    "type": "514",
                    "detail": "1374208",
                    "data": "0"
                },
                {
                    "position": {
                        "x": "0.885826766",
                        "y": "0.944999993"
                    },
                    "ms": "13202",
                    "type": "513",
                    "detail": "1374208",
                    "data": "0"
                },
                {
                    "position": {
                        "x": "0.885826766",
                        "y": "0.944000006"
                    },
                    "ms": "13235",
                    "type": "512",
                    "detail": "1374208",
                    "data": "0"
                },
                {
                    "position": {
                        "x": "0.885826766",
                        "y": "0.944000006"
                    },
                    "ms": "13302",
                    "type": "514",
                    "detail": "1374208",
                    "data": "0"
                },
                {
                    "position": {
                        "x": "0.883577049",
                        "y": "0.943000019"
                    },
                    "ms": "13386",
                    "type": "513",
                    "detail": "1374208",
                    "data": "0"
                },
                {
                    "position": {
                        "x": "0.883577049",
                        "y": "0.941999972"
                    },
                    "ms": "13392",
                    "type": "512",
                    "detail": "1374208",
                    "data": "0"
                },
                {
                    "position": {
                        "x": "0.883577049",
                        "y": "0.941999972"
                    },
                    "ms": "13470",
                    "type": "514",
                    "detail": "1374208",
                    "data": "0"
                },
                {
                    "position": {
                        "x": "0.883577049",
                        "y": "0.941999972"
                    },
                    "ms": "13519",
                    "type": "513",
                    "detail": "1374208",
                    "data": "0"
                },
                {
                    "position": {
                        "x": "0.883577049",
                        "y": "0.941999972"
                    },
                    "ms": "13621",
                    "type": "514",
                    "detail": "1374208",
                    "data": "0"
                },
                {
                    "position": {
                        "x": "0.883577049",
                        "y": "0.941999972"
                    },
                    "ms": "13687",
                    "type": "513",
                    "detail": "1374208",
                    "data": "0"
                },
                {
                    "position": {
                        "x": "0.883577049",
                        "y": "0.941999972"
                    },
                    "ms": "13788",
                    "type": "514",
                    "detail": "1374208",
                    "data": "0"
                },
                {
                    "position": {
                        "x": "0.883577049",
                        "y": "0.941999972"
                    },
                    "ms": "13858",
                    "type": "513",
                    "detail": "1374208",
                    "data": "0"
                },
                {
                    "position": {
                        "x": "0.883577049",
                        "y": "0.941999972"
                    },
                    "ms": "13938",
                    "type": "514",
                    "detail": "1374208",
                    "data": "0"
                },
                {
                    "position": {
                        "x": "0.485939264",
                        "y": "0.140000001"
                    },
                    "ms": "14496",
                    "type": "513",
                    "detail": "1374208",
                    "data": "0"
                },
                {
                    "position": {
                        "x": "0.485939264",
                        "y": "0.140000001"
                    },
                    "ms": "14587",
                    "type": "514",
                    "detail": "1374208",
                    "data": "0"
                },
                {
                    "position": {
                        "x": "0.485939264",
                        "y": "0.140000001"
                    },
                    "ms": "14651",
                    "type": "513",
                    "detail": "1374208",
                    "data": "0"
                },
                {
                    "position": {
                        "x": "0.485939264",
                        "y": "0.140000001"
                    },
                    "ms": "14751",
                    "type": "514",
                    "detail": "1374208",
                    "data": "0"
                },
                {
                    "position": {
                        "x": "0.485939264",
                        "y": "0.140000001"
                    },
                    "ms": "14801",
                    "type": "513",
                    "detail": "1374208",
                    "data": "0"
                },
                {
                    "position": {
                        "x": "0.485939264",
                        "y": "0.140000001"
                    },
                    "ms": "14900",
                    "type": "514",
                    "detail": "1374208",
                    "data": "0"
                },
                {
                    "position": {
                        "x": "0.893700778",
                        "y": "0.268999994"
                    },
                    "ms": "15413",
                    "type": "513",
                    "detail": "1374208",
                    "data": "0"
                },
                {
                    "position": {
                        "x": "0.893700778",
                        "y": "0.268999994"
                    },
                    "ms": "15513",
                    "type": "514",
                    "detail": "1374208",
                    "data": "0"
                },
                {
                    "position": {
                        "x": "0.89257592",
                        "y": "0.268999994"
                    },
                    "ms": "16218",
                    "type": "513",
                    "detail": "1374208",
                    "data": "0"
                },
                {
                    "position": {
                        "x": "0.89257592",
                        "y": "0.268999994"
                    },
                    "ms": "16318",
                    "type": "514",
                    "detail": "1374208",
                    "data": "0"
                },
                {
                    "position": {
                        "x": "0.917322814",
                        "y": "0.379000008"
                    },
                    "ms": "17186",
                    "type": "513",
                    "detail": "1374208",
                    "data": "0"
                },
                {
                    "position": {
                        "x": "0.917322814",
                        "y": "0.379000008"
                    },
                    "ms": "17288",
                    "type": "514",
                    "detail": "1374208",
                    "data": "0"
                },
                {
                    "position": {
                        "x": "0.917322814",
                        "y": "0.379000008"
                    },
                    "ms": "18049",
                    "type": "513",
                    "detail": "1374208",
                    "data": "0"
                },
                {
                    "position": {
                        "x": "0.917322814",
                        "y": "0.379000008"
                    },
                    "ms": "18147",
                    "type": "514",
                    "detail": "1374208",
                    "data": "0"
                },
                {
                    "position": {
                        "x": "0.903824508",
                        "y": "0.505999982"
                    },
                    "ms": "18985",
                    "type": "513",
                    "detail": "1374208",
                    "data": "0"
                },
                {
                    "position": {
                        "x": "0.903824508",
                        "y": "0.505999982"
                    },
                    "ms": "19084",
                    "type": "514",
                    "detail": "1374208",
                    "data": "0"
                },
                {
                    "position": {
                        "x": "0.903824508",
                        "y": "0.505999982"
                    },
                    "ms": "19939",
                    "type": "513",
                    "detail": "1374208",
                    "data": "0"
                },
                {
                    "position": {
                        "x": "0.903824508",
                        "y": "0.505999982"
                    },
                    "ms": "20055",
                    "type": "514",
                    "detail": "1374208",
                    "data": "0"
                },
                {
                    "position": {
                        "x": "0.626546681",
                        "y": "0.147"
                    },
                    "ms": "20756",
                    "type": "513",
                    "detail": "1374208",
                    "data": "0"
                },
                {
                    "position": {
                        "x": "0.626546681",
                        "y": "0.147"
                    },
                    "ms": "20838",
                    "type": "514",
                    "detail": "1374208",
                    "data": "0"
                },
                {
                    "position": {
                        "x": "0.626546681",
                        "y": "0.147"
                    },
                    "ms": "20908",
                    "type": "513",
                    "detail": "1374208",
                    "data": "0"
                },
                {
                    "position": {
                        "x": "0.626546681",
                        "y": "0.147"
                    },
                    "ms": "20990",
                    "type": "514",
                    "detail": "1374208",
                    "data": "0"
                },
                {
                    "position": {
                        "x": "0.626546681",
                        "y": "0.147"
                    },
                    "ms": "21056",
                    "type": "513",
                    "detail": "1374208",
                    "data": "0"
                },
                {
                    "position": {
                        "x": "0.626546681",
                        "y": "0.147"
                    },
                    "ms": "21141",
                    "type": "514",
                    "detail": "1374208",
                    "data": "0"
                },
                {
                    "position": {
                        "x": "0.52924633",
                        "y": "0.246000007"
                    },
                    "ms": "21952",
                    "type": "513",
                    "detail": "1374208",
                    "data": "0"
                },
                {
                    "position": {
                        "x": "0.52924633",
                        "y": "0.246000007"
                    },
                    "ms": "22035",
                    "type": "514",
                    "detail": "1374208",
                    "data": "0"
                },
                {
                    "position": {
                        "x": "0.52924633",
                        "y": "0.246000007"
                    },
                    "ms": "22301",
                    "type": "513",
                    "detail": "1374208",
                    "data": "0"
                },
                {
                    "position": {
                        "x": "0.52924633",
                        "y": "0.246000007"
                    },
                    "ms": "22403",
                    "type": "514",
                    "detail": "1374208",
                    "data": "0"
                },
                {
                    "position": {
                        "x": "0.52924633",
                        "y": "0.246000007"
                    },
                    "ms": "23274",
                    "type": "513",
                    "detail": "1374208",
                    "data": "0"
                },
                {
                    "position": {
                        "x": "0.52924633",
                        "y": "0.246000007"
                    },
                    "ms": "23371",
                    "type": "514",
                    "detail": "1374208",
                    "data": "0"
                },
                {
                    "position": {
                        "x": "0.52924633",
                        "y": "0.246000007"
                    },
                    "ms": "23685",
                    "type": "513",
                    "detail": "1374208",
                    "data": "0"
                },
                {
                    "position": {
                        "x": "0.52924633",
                        "y": "0.246000007"
                    },
                    "ms": "23784",
                    "type": "514",
                    "detail": "1374208",
                    "data": "0"
                },
                {
                    "position": {
                        "x": "0.52924633",
                        "y": "0.246000007"
                    },
                    "ms": "24568",
                    "type": "513",
                    "detail": "1374208",
                    "data": "0"
                },
                {
                    "position": {
                        "x": "0.52924633",
                        "y": "0.246000007"
                    },
                    "ms": "24684",
                    "type": "514",
                    "detail": "1374208",
                    "data": "0"
                },
                {
                    "position": {
                        "x": "0.52924633",
                        "y": "0.246000007"
                    },
                    "ms": "24919",
                    "type": "513",
                    "detail": "1374208",
                    "data": "0"
                },
                {
                    "position": {
                        "x": "0.52924633",
                        "y": "0.246000007"
                    },
                    "ms": "25020",
                    "type": "514",
                    "detail": "1374208",
                    "data": "0"
                },
                {
                    "position": {
                        "x": "0.52924633",
                        "y": "0.246000007"
                    },
                    "ms": "25841",
                    "type": "513",
                    "detail": "1374208",
                    "data": "0"
                },
                {
                    "position": {
                        "x": "0.52924633",
                        "y": "0.246000007"
                    },
                    "ms": "25940",
                    "type": "514",
                    "detail": "1374208",
                    "data": "0"
                },
                {
                    "position": {
                        "x": "0.52924633",
                        "y": "0.246000007"
                    },
                    "ms": "26453",
                    "type": "513",
                    "detail": "1374208",
                    "data": "0"
                },
                {
                    "position": {
                        "x": "0.52924633",
                        "y": "0.246000007"
                    },
                    "ms": "26555",
                    "type": "514",
                    "detail": "1374208",
                    "data": "0"
                },
                {
                    "position": {
                        "x": "0.52924633",
                        "y": "0.246000007"
                    },
                    "ms": "27471",
                    "type": "513",
                    "detail": "1374208",
                    "data": "0"
                },
                {
                    "position": {
                        "x": "0.52924633",
                        "y": "0.246000007"
                    },
                    "ms": "27572",
                    "type": "514",
                    "detail": "1374208",
                    "data": "0"
                },
                {
                    "position": {
                        "x": "0.52924633",
                        "y": "0.246000007"
                    },
                    "ms": "27908",
                    "type": "513",
                    "detail": "1374208",
                    "data": "0"
                },
                {
                    "position": {
                        "x": "0.52924633",
                        "y": "0.246000007"
                    },
                    "ms": "28006",
                    "type": "514",
                    "detail": "1374208",
                    "data": "0"
                },
                {
                    "position": {
                        "x": "0.956130505",
                        "y": "0.0670000017"
                    },
                    "ms": "28946",
                    "type": "513",
                    "detail": "1374208",
                    "data": "0"
                },
                {
                    "position": {
                        "x": "0.956130505",
                        "y": "0.0670000017"
                    },
                    "ms": "29030",
                    "type": "514",
                    "detail": "1374208",
                    "data": "0"
                },
                {
                    "position": {
                        "x": "0",
                        "y": "0"
                    },
                    "ms": "29813",
                    "type": "18446744073709551615",
                    "detail": "0",
                    "data": "0"
                }
            ]
        }
    }
}
